avatar_creator/__init__.py
avatar_creator/core.py
avatar_creator_core-1.0.1.dist-info/licenses/LICENSE
avatar_creator_core-1.0.1.dist-info/METADATA
avatar_creator_core-1.0.1.dist-info/WHEEL
avatar_creator_core-1.0.1.dist-info/top_level.txt
avatar_creator_core-1.0.1.dist-info/RECORD
