Metadata-Version: 2.4
Name: avatar-creator-core
Version: 1.0.1
Summary: Recolor white-hair assets & composite avatars
Home-page: https://github.com/Darker21/avatar-creator-core
Author: Jacob Darker
Author-email: jacob@darker.software
License: "MIT"
Classifier: Programming Language :: Python :: 3
License-File: LICENSE
Requires-Dist: Pillow>=9.0.0
Dynamic: license-file
